typhoon_dbapi/__init__.py
typhoon_dbapi/functions/__init__.py
typhoon_dbapi/functions/bulk.py
typhoon_dbapi/functions/relational.py
typhoon_dbapi/functions/snowflake.py
typhoon_dbapi/hooks/__init__.py
typhoon_dbapi/hooks/dbapi_hooks.py
typhoon_dbapi/hooks/sqlalchemy_hook.py
typhoon_dbapi/templates/__init__.py
typhoon_dbapi/templates/snowflake.py
typhoon_dbapi-0.0.3.dist-info/METADATA
typhoon_dbapi-0.0.3.dist-info/WHEEL
typhoon_dbapi-0.0.3.dist-info/top_level.txt
typhoon_dbapi-0.0.3.dist-info/RECORD
