Metadata-Version: 2.1
Name: typhoon-dbapi
Version: 0.0.3
Summary: Hooks and functions related to databases compatible with the Python Database API Specification v2.0.
Home-page: https://github.com/pypa/sampleproject
Author: Typhoon Data
Author-email: info.typhoon.data@gmail.com
License: UNKNOWN
Project-URL: Bug Tracker, https://github.com/pypa/sampleproject/issues
Platform: UNKNOWN
Classifier: Programming Language :: Python :: 3
Classifier: License :: OSI Approved :: Apache Software License
Classifier: Operating System :: OS Independent
Requires-Python: >=3.6
Requires-Dist: typhoon-orchestrator
Requires-Dist: sqlparse
Provides-Extra: bigquery
Requires-Dist: google-cloud-bigquery ; extra == 'bigquery'
Provides-Extra: duckdb
Requires-Dist: duckdb ; extra == 'duckdb'
Provides-Extra: mssql
Requires-Dist: pymssql ; extra == 'mssql'
Provides-Extra: mysql
Requires-Dist: mysql-connector-python ; extra == 'mysql'
Provides-Extra: postgres
Requires-Dist: psycopg2 ; extra == 'postgres'
Provides-Extra: snowflake
Requires-Dist: snowflake-connector-python ; extra == 'snowflake'
Provides-Extra: sqlalchemy
Requires-Dist: sqlalchemy ; extra == 'sqlalchemy'
